[
  {
    "_id": "d1",
    "name": "Boris Groh"
  },
  {
    "_id": "d2",
    "name": "Oleksandr Nikitiuk"
  },
  {
    "_id": "d3",
    "name": "Anton Prusov"
  },
  {
    "_id": "d4",
    "name": "Volodymyr Taran"
  },
  {
    "_id": "d5",
    "name": "Oleksandr Kharuk"
  },
  {
    "_id": "d6",
    "name": "Serhiy Kharuk"
  },
  {
    "_id": "d7",
    "name": "Serhiy Reznichenko"
  },
  {
    "_id": "d8",
    "name": "Yuriy Shapoval"
  },
  {
    "_id": "d9",
    "name": "Nikita Titov"
  },
  {
    "_id": "d10",
    "name": "Anastasia Bondarets"
  },
  {
    "_id": "d11",
    "name": "Anton Liakhov"
  },
  {
    "_id": "d12",
    "name": "Olesia Vakulenko"
  },
  {
    "_id": "d13",
    "name": "Mykola Kochubey"
  },
  {
    "_id": "d14",
    "name": "Nataliia Kokhal"
  },
  {
    "_id": "d15",
    "name": "Oleksandr Kuzmin"
  },
  {
    "_id": "d16",
    "name": "Mariia Kuzmina"
  },
  {
    "_id": "d17",
    "name": "Nataliia Andriichenko"
  },
  {
    "_id": "d18",
    "name": "Vasyl Vasylenko"
  },
  {
    "_id": "d19",
    "name": "Oksana Shuklinova"
  },
  {
    "_id": "d20",
    "name": "Maryna Kuts"
  },
  {
    "_id": "d21",
    "name": "Sofia Kravchuk"
  },
  {
    "_id": "d22",
    "name": "Anton Khrupin"
  },
  {
    "_id": "d23",
    "name": "Andriy Sahach"
  },
  {
    "_id": "d24",
    "name": "Valeriia Mykhailova"
  },
  {
    "_id": "d25",
    "name": "Banksy"
  },
  {
    "_id": "d26",
    "name": "Kseniia Datsiuk"
  },
  {
    "_id": "d27",
    "name": "Kost Lavro"
  },
  {
    "_id": "d28",
    "name": "Olena Glazunova"
  },
  {
    "_id": "d29",
    "name": "Zinaida Kubar"
  },
  {
    "_id": "d30",
    "name": "Viktor Kudin"
  },
  {
    "_id": "d31",
    "name": "Maksym Palenko"
  },
  {
    "_id": "d32",
    "name": "Volodymyr Kononov"
  },
  {
    "_id": "d33",
    "name": "Oleksandr Okhapkin"
  },
  {
    "_id": "d34",
    "name": "I AM IDEA Creative Agency"
  },
  {
    "_id": "d35",
    "name": "Oleh Shupliak"
  },
  {
    "_id": "d36",
    "name": "Korneliia Andriichuk"
  },
  {
    "_id": "d37",
    "name": "Nato Mikeladze"
  },
  {
    "_id": "d38",
    "name": "Sofiia Riabokon"
  },
  {
    "_id": "d39",
    "name": "Viktor Hrudakov"
  },
  {
    "_id": "d40",
    "name": "Mariia Suslova"
  },
  {
    "_id": "d41",
    "name": "Linda Bos"
  },
  {
    "_id": "d42",
    "name": "Runa Egilsdottir"
  },
  {
    "_id": "d43",
    "name": "Sviatoslav Romanchak"
  },
  {
    "_id": "d44",
    "name": "Serhiy Nuzhnenko"
  },
  {
    "_id": "d45",
    "name": "Mykhailo Dzhos"
  }
]